AsyncHttpX/__init__.py
asynchttpx-0.0.2.dist-info/METADATA
asynchttpx-0.0.2.dist-info/WHEEL
asynchttpx-0.0.2.dist-info/licenses/LICENSE
asynchttpx-0.0.2.dist-info/RECORD
