Metadata-Version: 2.4
Name: AsyncHttpX
Version: 0.0.2
Summary: AsyncHttpX Library is a high-performance, asynchronous HTTP client built on top of the powerful httpx library. Designed for developers who need a robust and flexible way to make HTTP requests in Python
Project-URL: Homepage, https://github.com/ToolParadiseDrako/Nuker-Tool-Paradise
Project-URL: Issues, https://github.com/ToolParadiseDrako/Nuker-Tool-Paradise
Author-email: Vke <wragpiszon2022@gmail.com>
License-File: LICENSE
Classifier: License :: OSI Approved :: GNU General Public License v3 (GPLv3)
Classifier: Operating System :: OS Independent
Classifier: Programming Language :: Python :: 3
Requires-Python: >=3.0
